ingest_data.py
nonstandardcode.py
score.py
train.py
housingLibrary_5508-0.1.dist-info/METADATA
housingLibrary_5508-0.1.dist-info/WHEEL
housingLibrary_5508-0.1.dist-info/entry_points.txt
housingLibrary_5508-0.1.dist-info/top_level.txt
housingLibrary_5508-0.1.dist-info/RECORD
