Metadata-Version: 2.1
Name: housingLibrary_5508
Version: 0.1
Summary: Sample code for coding practice
Author-email: Viswas <viswas.kodati@tigeranalytics.com>
Project-URL: Homepage, https://github.com/viswas-tiger/mle-training
Keywords: housing,data training
Classifier: Programming Language :: Python :: 3
Requires-Python: >=3.11
Requires-Dist: numpy
Requires-Dist: pandas
Requires-Dist: scikit-learn
